{"_default": {"1": {"app_name": "Application2", "version": "1.0", "location": "", "os": "os_1"}, "2": {"app_name": "Application1", "version": "1.0", "location": "", "os": "os_1"}, "3": {"app_name": "Application3", "version": "1.0", "location": "", "os": "os_1"}, "4": {"app_name": "Application1", "version": "2.0", "location": "", "os": "os_1"}, "5": {"app_name": "Application1", "version": "2.0", "location": "", "os": "os_1"}, "6": {"app_name": "Application1", "version": "4.0", "location": "", "os": "os_1"}}}